metanno/.DS_Store
metanno/__init__.py
metanno/base.py
metanno/immutable.py
metanno/manager.py
metanno/python_to_javascript.py
metanno/utils.py
metanno/views.py
metanno/connectors/__init__.py
metanno/connectors/brat.py
metanno/labextension/build_log.json
metanno/labextension/package.json
metanno/labextension/schemas/metanno/dontDisplayHiddenOutput.js
metanno/labextension/schemas/metanno/loadTranscypt.js
metanno/labextension/schemas/metanno/manager.js
metanno/labextension/schemas/metanno/metanno.css
metanno/labextension/schemas/metanno/org.transcrypt.__runtime__.js
metanno/labextension/schemas/metanno/package.json.orig
metanno/labextension/schemas/metanno/plugin.js
metanno/labextension/schemas/metanno/plugin.json
metanno/labextension/schemas/metanno/renderer.js
metanno/labextension/static/10.70647a421f55cb9c5277.js
metanno/labextension/static/132.64452015322b8e22f882.js
metanno/labextension/static/172.741e8a3e57ba350b4957.js
metanno/labextension/static/278.e7a307b8908f4360bb3f.js
metanno/labextension/static/278.e7a307b8908f4360bb3f.js.LICENSE.txt
metanno/labextension/static/31.66731c3e846943f71a62.js
metanno/labextension/static/402.20f67cd12aced0dddedd.js
metanno/labextension/static/402.20f67cd12aced0dddedd.js.LICENSE.txt
metanno/labextension/static/453.b4c712960ac4fc936b9d.js
metanno/labextension/static/480.b9b8038cfd767a21b44f.js
metanno/labextension/static/480.b9b8038cfd767a21b44f.js.LICENSE.txt
metanno/labextension/static/546.cdccf3d18c5111c4ebf4.js
metanno/labextension/static/568.279fcb697827da5a6548.js
metanno/labextension/static/568.30b6af755c5ce82f8952.js
metanno/labextension/static/568.624892779399838a87bd.js
metanno/labextension/static/582.6e6ebea5800f6b766941.js
metanno/labextension/static/587.83b3cbfbe2f81086aaf6.js
metanno/labextension/static/590.92a585127a84eb0cc81c.js
metanno/labextension/static/623.5017c07483f0f4f8b0e2.js
metanno/labextension/static/632.3fa96eec56dc9e161d52.js
metanno/labextension/static/744.6d20f46448e3db69667d.js
metanno-0.0.9.dist-info/LICENSE
metanno-0.0.9.dist-info/METADATA
metanno-0.0.9.dist-info/WHEEL
metanno-0.0.9.dist-info/top_level.txt
metanno-0.0.9.dist-info/RECORD
