Metadata-Version: 2.1
Name: metanno
Version: 0.0.9
Summary: Jupyter widgets collection to setup a modular annotation environment
Home-page: https://github.com/percevalw/metanno
Author: Perceval Wajsburt
Author-email: perceval.wajsburt@sorbonne-universite.fr
License: MIT
Keywords: Jupyter,JupyterLab
Platform: Linux
Platform: Mac OS X
Platform: Windows
Classifier: License :: OSI Approved :: MIT License
Classifier: Operating System :: OS Independent
Classifier: Programming Language :: Python
Classifier: Programming Language :: Python :: 3
Classifier: Programming Language :: Python :: 3.8
Classifier: Programming Language :: Python :: 3.9
Classifier: Framework :: Jupyter
Requires-Python: >=3.6
Requires-Dist: transcrypt (==3.9.0)
Requires-Dist: ipykernel
Requires-Dist: astunparse
